Workbook

Sheet Dashboard Summary
A1: CDS EXAM MASTER SYLLABUS & PROGRESS DASHBOARD
A2: Track chapter completion, practice marks, and multi-stage revisions across all subjects
A4: SUBJECT LEVEL PROGRESS OVERVIEW
A5: Subject Name | B5: Total Chapters | C5: Completed | D5: In Progress | E5: Not Started | F5: Completion % | G5: Avg Practice Score | H5: Rev 1 Done | I5: Rev 2 Done | J5: Rev 3 Done
A6: Elementary Mathematics | B6: =COUNTA('Elementary Mathematics'!A6:A100) | C6: =COUNTIF('Elementary Mathematics'!E6:E100, "Completed") | D6: =COUNTIF('Elementary Mathematics'!E6:E100, "In Progress") | E6: =COUNTIF('Elementary Mathematics'!E6:E100, "Not Started") | F6: =C6/B6 | G6: =AVERAGE('Elementary Mathematics'!G6:G100) | H6: =COUNTIF('Elementary Mathematics'!H6:H100, "Yes") | I6: =COUNTIF('Elementary Mathematics'!I6:I100, "Yes") | J6: =COUNTIF('Elementary Mathematics'!J6:J100, "Yes")
A7: Physics | B7: =COUNTA('Physics'!A6:A100) | C7: =COUNTIF('Physics'!E6:E100, "Completed") | D7: =COUNTIF('Physics'!E6:E100, "In Progress") | E7: =COUNTIF('Physics'!E6:E100, "Not Started") | F7: =C7/B7 | G7: =AVERAGE('Physics'!G6:G100) | H7: =COUNTIF('Physics'!H6:H100, "Yes") | I7: =COUNTIF('Physics'!I6:I100, "Yes") | J7: =COUNTIF('Physics'!J6:J100, "Yes")
A8: History | B8: =COUNTA('History'!A6:A100) | C8: =COUNTIF('History'!E6:E100, "Completed") | D8: =COUNTIF('History'!E6:E100, "In Progress") | E8: =COUNTIF('History'!E6:E100, "Not Started") | F8: =C8/B8 | G8: =AVERAGE('History'!G6:G100) | H8: =COUNTIF('History'!H6:H100, "Yes") | I8: =COUNTIF('History'!I6:I100, "Yes") | J8: =COUNTIF('History'!J6:J100, "Yes")
A9: Geography | B9: =COUNTA('Geography'!A6:A100) | C9: =COUNTIF('Geography'!E6:E100, "Completed") | D9: =COUNTIF('Geography'!E6:E100, "In Progress") | E9: =COUNTIF('Geography'!E6:E100, "Not Started") | F9: =C9/B9 | G9: =AVERAGE('Geography'!G6:G100) | H9: =COUNTIF('Geography'!H6:H100, "Yes") | I9: =COUNTIF('Geography'!I6:I100, "Yes") | J9: =COUNTIF('Geography'!J6:J100, "Yes")
A10: Indian Polity | B10: =COUNTA('Indian Polity'!A6:A100) | C10: =COUNTIF('Indian Polity'!E6:E100, "Completed") | D10: =COUNTIF('Indian Polity'!E6:E100, "In Progress") | E10: =COUNTIF('Indian Polity'!E6:E100, "Not Started") | F10: =C10/B10 | G10: =AVERAGE('Indian Polity'!G6:G100) | H10: =COUNTIF('Indian Polity'!H6:H100, "Yes") | I10: =COUNTIF('Indian Polity'!I6:I100, "Yes") | J10: =COUNTIF('Indian Polity'!J6:J100, "Yes")
A11: Indian Economy | B11: =COUNTA('Indian Economy'!A6:A100) | C11: =COUNTIF('Indian Economy'!E6:E100, "Completed") | D11: =COUNTIF('Indian Economy'!E6:E100, "In Progress") | E11: =COUNTIF('Indian Economy'!E6:E100, "Not Started") | F11: =C11/B11 | G11: =AVERAGE('Indian Economy'!G6:G100) | H11: =COUNTIF('Indian Economy'!H6:H100, "Yes") | I11: =COUNTIF('Indian Economy'!I6:I100, "Yes") | J11: =COUNTIF('Indian Economy'!J6:J100, "Yes")
A12: General Knowledge | B12: =COUNTA('General Knowledge'!A6:A100) | C12: =COUNTIF('General Knowledge'!E6:E100, "Completed") | D12: =COUNTIF('General Knowledge'!E6:E100, "In Progress") | E12: =COUNTIF('General Knowledge'!E6:E100, "Not Started") | F12: =C12/B12 | G12: =AVERAGE('General Knowledge'!G6:G100) | H12: =COUNTIF('General Knowledge'!H6:H100, "Yes") | I12: =COUNTIF('General Knowledge'!I6:I100, "Yes") | J12: =COUNTIF('General Knowledge'!J6:J100, "Yes")
A13: TOTAL / OVERALL | B13: =SUM(B6:B12) | C13: =SUM(C6:C12) | D13: =SUM(D6:D12) | E13: =SUM(E6:E12) | F13: =C13/B13 | G13: =AVERAGE(G6:G12) | H13: =SUM(H6:H12) | I13: =SUM(I6:I12) | J13: =SUM(J6:J12)

Sheet Elementary Mathematics
A1: ELEMENTARY MATHEMATICS - CHAPTER SYLLABUS & TRACKER
A2: Select Status and Revision drop-downs. Enter Practice Marks to auto-calculate percentages.
A4: Total Chapters: | B4: =COUNTA(A6:A33) | D4: Completed: | E4: =COUNTIF(E6:E33, "Completed") | G4: Progress %: | H4: =E4/B4 | J4: Avg Practice Score: | K4: =AVERAGE(F6:F33)
A5: Chapter Code | B5: Chapter Title | C5: Sub-topics & Key Concepts | D5: Priority | E5: Status (Checkmark) | F5: Practice Score (%) | G5: Practice Marks (Obtained / Max) | H5: Revision 1 | I5: Revision 2 | J5: Revision 3 | K5: Notes / Weak Areas
A6: Ch 01 | B6: Number System | C6: Number Theory, Divisibility, Prime Numbers, Factors | D6: Medium | E6: Not Started | F6: =IF(G6>0, G6/10, 0) | G6: 0 | H6: No | I6: No | J6: No
A7: Ch 02 | B7: Sequence and Series | C7: Arithmetic Progression (AP), Geometric Progression (GP) | D7: Medium | E7: Not Started | F7: =IF(G7>0, G7/8, 0) | G7: 0 | H7: No | I7: No | J7: No
A8: Ch 03 | B8: HCF and LCM of Numbers | C8: Prime Factorization, Division Method, Word Problems | D8: Medium | E8: Not Started | F8: =IF(G8>0, G8/8, 0) | G8: 0 | H8: No | I8: No | J8: No
A9: Ch 04 | B9: Modular Arithmetic & Remainders | C9: Remainder Theorems, Congruence, Euler Totient | D9: Medium | E9: Not Started | F9: =IF(G9>0, G9/6, 0) | G9: 0 | H9: No | I9: No | J9: No
A10: Ch 05 | B10: Square Roots and Cube Roots | C10: Simplification, Surds and Indices, Approximations | D10: Medium | E10: Not Started | F10: =IF(G10>0, G10/6, 0) | G10: 0 | H10: No | I10: No | J10: No
A11: Ch 06 | B11: Time and Distance | C11: Speed, Distance, Trains, Boats & Streams, Relative Speed | D11: Medium | E11: Not Started | F11: =IF(G11>0, G11/10, 0) | G11: 0 | H11: No | I11: No | J11: No
A12: Ch 07 | B12: Time and Work | C12: Work Efficiency, Pipes and Cisterns, Alternative Days | D12: Medium | E12: Not Started | F12: =IF(G12>0, G12/10, 0) | G12: 0 | H12: No | I12: No | J12: No
A13: Ch 08 | B13: Percentage | C13: Percentage Increase/Decrease, Population, Successive Change | D13: Medium | E13: Not Started | F13: =IF(G13>0, G13/10, 0) | G13: 0 | H13: No | I13: No | J13: No
A14: Ch 09 | B14: Simple Interest | C14: Principal, Rate, Time, Compound Interest comparison | D14: Medium | E14: Not Started | F14: =IF(G14>0, G14/8, 0) | G14: 0 | H14: No | I14: No | J14: No
A15: Ch 10 | B15: Compound Interest | C15: Effective Rate, Difference between CI & SI | D15: Medium | E15: Not Started | F15: =IF(G15>0, G15/8, 0) | G15: 0 | H15: No | I15: No | J15: No
A16: Ch 11 | B16: Profit and Loss | C16: Cost Price, Selling Price, Discount, Marked Price | D16: Medium | E16: Not Started | F16: =IF(G16>0, G16/10, 0) | G16: 0 | H16: No | I16: No | J16: No
A17: Ch 12 | B17: Ratio and Proportion | C17: Direct & Inverse Variation, Mixtures & Alligations, Ages | D17: Medium | E17: Not Started | F17: =IF(G17>0, G17/10, 0) | G17: 0 | H17: No | I17: No | J17: No
A18: Ch 13 | B18: Logarithms | C18: Properties of Logarithms, Logarithmic Equations | D18: Medium | E18: Not Started | F18: =IF(G18>0, G18/6, 0) | G18: 0 | H18: No | I18: No | J18: No
A19: Ch 14 | B19: Basic Algebra | C19: Algebraic Identities, Polynomial Operations | D19: Medium | E19: Not Started | F19: =IF(G19>0, G19/8, 0) | G19: 0 | H19: No | I19: No | J19: No
A20: Ch 15 | B20: HCF and LCM of Polynomials | C20: Factorization of Polynomials, Common Factors | D20: Medium | E20: Not Started | F20: =IF(G20>0, G20/6, 0) | G20: 0 | H20: No | I20: No | J20: No
A21: Ch 16 | B21: Rational Expressions | C21: Simplification, Partial Fractions, Algebraic Expressions | D21: Medium | E21: Not Started | F21: =IF(G21>0, G21/6, 0) | G21: 0 | H21: No | I21: No | J21: No
A22: Ch 17 | B22: Linear Equations | C22: Equations in 1 & 2 Variables, Word Problems | D22: Medium | E22: Not Started | F22: =IF(G22>0, G22/8, 0) | G22: 0 | H22: No | I22: No | J22: No
A23: Ch 18 | B23: Quadratic Equations & Inequalities | C23: Roots, Discriminant, Nature of Roots, Quadratic Curves | D23: Medium | E23: Not Started | F23: =IF(G23>0, G23/10, 0) | G23: 0 | H23: No | I23: No | J23: No
A24: Ch 19 | B24: Set Theory | C24: Venn Diagrams, Subsets, Operations on Sets | D24: Medium | E24: Not Started | F24: =IF(G24>0, G24/6, 0) | G24: 0 | H24: No | I24: No | J24: No
A25: Ch 20 | B25: Trigonometric Ratios & Angles | C25: Identities, Specific Angles, Standard Values | D25: High | E25: Not Started | F25: =IF(G25>0, G25/12, 0) | G25: 0 | H25: No | I25: No | J25: No
A26: Ch 21 | B26: Trigonometric Identities & Equations | C26: Compound Angles, Transformations, Conditional Identities | D26: Medium | E26: Not Started | F26: =IF(G26>0, G26/10, 0) | G26: 0 | H26: No | I26: No | J26: No
A27: Ch 22 | B27: Heights and Distances | C27: Angle of Elevation, Angle of Depression, Shadow Problems | D27: Medium | E27: Not Started | F27: =IF(G27>0, G27/10, 0) | G27: 0 | H27: No | I27: No | J27: No
A28: Ch 23 | B28: Triangles | C28: Congruence, Similarity, Centers of Triangle, Pythagoras | D28: High | E28: Not Started | F28: =IF(G28>0, G28/12, 0) | G28: 0 | H28: No | I28: No | J28: No
A29: Ch 24 | B29: Quadrilateral and Polygon | C29: Parallelogram, Rectangle, Rhombus, Polygons Properties | D29: Medium | E29: Not Started | F29: =IF(G29>0, G29/10, 0) | G29: 0 | H29: No | I29: No | J29: No
A30: Ch 25 | B30: Circle | C30: Chords, Tangents, Angles in Segments, Cyclic Quadrilaterals | D30: High | E30: Not Started | F30: =IF(G30>0, G30/12, 0) | G30: 0 | H30: No | I30: No | J30: No
A31: Ch 26 | B31: Area and Perimeter (2D) | C31: Triangles, Circles, Quadrilaterals, Shaded Regions | D31: High | E31: Not Started | F31: =IF(G31>0, G31/12, 0) | G31: 0 | H31: No | I31: No | J31: No
A32: Ch 27 | B32: Surface Area and Volume (3D) | C32: Cylinder, Cone, Sphere, Prism, Pyramid, Frustum | D32: High | E32: Not Started | F32: =IF(G32>0, G32/12, 0) | G32: 0 | H32: No | I32: No | J32: No
A33: Ch 28 | B33: Statistics | C33: Mean, Median, Mode, Frequency Distribution, Histograms | D33: Medium | E33: Not Started | F33: =IF(G33>0, G33/8, 0) | G33: 0 | H33: No | I33: No | J33: No

Sheet Physics
A1: PHYSICS - CHAPTER SYLLABUS & TRACKER
A2: Select Status and Revision drop-downs. Enter Practice Marks to auto-calculate percentages.
A4: Total Chapters: | B4: =COUNTA(A6:A13) | D4: Completed: | E4: =COUNTIF(E6:E13, "Completed") | G4: Progress %: | H4: =E4/B4 | J4: Avg Practice Score: | K4: =AVERAGE(F6:F13)
A5: Chapter Code | B5: Chapter Title | C5: Sub-topics & Key Concepts | D5: Priority | E5: Status (Checkmark) | F5: Practice Score (%) | G5: Practice Marks (Obtained / Max) | H5: Revision 1 | I5: Revision 2 | J5: Revision 3 | K5: Notes / Weak Areas
A6: Ch 01 | B6: Mechanics & Dynamics | C6: Kinematics, Newton Laws, Momentum, Friction, Work, Energy & Power | D6: Medium | E6: Not Started | F6: =IF(G6>0, G6/10, 0) | G6: 0 | H6: No | I6: No | J6: No
A7: Ch 02 | B7: Gravitation & Rotational Motion | C7: Kepler Laws, Escape Velocity, Satellites, Torque, Angular Momentum | D7: Medium | E7: Not Started | F7: =IF(G7>0, G7/8, 0) | G7: 0 | H7: No | I7: No | J7: No
A8: Ch 03 | B8: Properties of Matter & Fluids | C8: Elasticity, Surface Tension, Viscosity, Pascal Law, Bernoulli Principle | D8: Medium | E8: Not Started | F8: =IF(G8>0, G8/8, 0) | G8: 0 | H8: No | I8: No | J8: No
A9: Ch 04 | B9: Heat & Thermodynamics | C9: Temperature Scales, Specific Heat, Latent Heat, Laws of Thermodynamics | D9: Medium | E9: Not Started | F9: =IF(G9>0, G9/8, 0) | G9: 0 | H9: No | I9: No | J9: No
A10: Ch 05 | B10: Oscillations & Waves | C10: Simple Harmonic Motion, Pendulum, Sound Waves, Doppler Effect | D10: Medium | E10: Not Started | F10: =IF(G10>0, G10/8, 0) | G10: 0 | H10: No | I10: No | J10: No
A11: Ch 06 | B11: Optics & Optical Instruments | C11: Reflection, Refraction, Lenses, Mirrors, Human Eye, Microscope, Telescope | D11: Medium | E11: Not Started | F11: =IF(G11>0, G11/10, 0) | G11: 0 | H11: No | I11: No | J11: No
A12: Ch 07 | B12: Electricity & Magnetism | C12: Ohm Law, Resistance, Kirchhoff Laws, Magnetic Field, Induction, AC | D12: Medium | E12: Not Started | F12: =IF(G12>0, G12/10, 0) | G12: 0 | H12: No | I12: No | J12: No
A13: Ch 08 | B13: Modern Physics & Communication | C13: Photoelectric Effect, Atomic Structure, Radioactivity, Semiconductors, Logic Gates | D13: Medium | E13: Not Started | F13: =IF(G13>0, G13/8, 0) | G13: 0 | H13: No | I13: No | J13: No

Sheet History
A1: HISTORY - CHAPTER SYLLABUS & TRACKER
A2: Select Status and Revision drop-downs. Enter Practice Marks to auto-calculate percentages.
A4: Total Chapters: | B4: =COUNTA(A6:A10) | D4: Completed: | E4: =COUNTIF(E6:E10, "Completed") | G4: Progress %: | H4: =E4/B4 | J4: Avg Practice Score: | K4: =AVERAGE(F6:F10)
A5: Chapter Code | B5: Chapter Title | C5: Sub-topics & Key Concepts | D5: Priority | E5: Status (Checkmark) | F5: Practice Score (%) | G5: Practice Marks (Obtained / Max) | H5: Revision 1 | I5: Revision 2 | J5: Revision 3 | K5: Notes / Weak Areas
A6: Ch 01 | B6: Ancient India | C6: Indus Valley, Vedic Age, Buddhism & Jainism, Maurya & Gupta Empire | D6: Medium | E6: Not Started | F6: =IF(G6>0, G6/10, 0) | G6: 0 | H6: No | I6: No | J6: No
A7: Ch 02 | B7: Medieval India | C7: Delhi Sultanate, Mughal Empire, Vijayanagara, Bhakti & Sufi Movements | D7: Medium | E7: Not Started | F7: =IF(G7>0, G7/10, 0) | G7: 0 | H7: No | I7: No | J7: No
A8: Ch 03 | B8: Modern India & Freedom Movement | C8: British Expansion, 1857 Revolt, INC, Gandhian Era, Independence 1947 | D8: High | E8: Not Started | F8: =IF(G8>0, G8/15, 0) | G8: 0 | H8: No | I8: No | J8: No
A9: Ch 04 | B9: World History | C9: Industrial Revolution, American & French Revolutions, WWI & WWII | D9: Medium | E9: Not Started | F9: =IF(G9>0, G9/6, 0) | G9: 0 | H9: No | I9: No | J9: No
A10: Ch 05 | B10: Art, Architecture & Culture | C10: Temple Architecture, Classical Dances, School of Art, Literature | D10: Medium | E10: Not Started | F10: =IF(G10>0, G10/8, 0) | G10: 0 | H10: No | I10: No | J10: No

Sheet Geography
A1: GEOGRAPHY - CHAPTER SYLLABUS & TRACKER
A2: Select Status and Revision drop-downs. Enter Practice Marks to auto-calculate percentages.
A4: Total Chapters: | B4: =COUNTA(A6:A11) | D4: Completed: | E4: =COUNTIF(E6:E11, "Completed") | G4: Progress %: | H4: =E4/B4 | J4: Avg Practice Score: | K4: =AVERAGE(F6:F11)
A5: Chapter Code | B5: Chapter Title | C5: Sub-topics & Key Concepts | D5: Priority | E5: Status (Checkmark) | F5: Practice Score (%) | G5: Practice Marks (Obtained / Max) | H5: Revision 1 | I5: Revision 2 | J5: Revision 3 | K5: Notes / Weak Areas
A6: Ch 01 | B6: Universe & Solar System | C6: Planetary Motions, Eclipses, Latitude & Longitude, Standard Time | D6: Medium | E6: Not Started | F6: =IF(G6>0, G6/6, 0) | G6: 0 | H6: No | I6: No | J6: No
A7: Ch 02 | B7: Geomorphology & Earth Interior | C7: Plate Tectonics, Earthquakes, Volcanoes, Rocks & Landforms | D7: Medium | E7: Not Started | F7: =IF(G7>0, G7/8, 0) | G7: 0 | H7: No | I7: No | J7: No
A8: Ch 03 | B8: Climatology & Atmosphere | C8: Atmospheric Layers, Winds, Pressure Belts, Rainfall, Cyclones | D8: Medium | E8: Not Started | F8: =IF(G8>0, G8/8, 0) | G8: 0 | H8: No | I8: No | J8: No
A9: Ch 04 | B9: Oceanography | C9: Ocean Relief, Salinity, Ocean Currents, Tides | D9: Medium | E9: Not Started | F9: =IF(G9>0, G9/6, 0) | G9: 0 | H9: No | I9: No | J9: No
A10: Ch 05 | B10: Indian Physical Geography | C10: Physiographic Divisions, Rivers & Drainage Systems, Climate & Soils | D10: High | E10: Not Started | F10: =IF(G10>0, G10/12, 0) | G10: 0 | H10: No | I10: No | J10: No
A11: Ch 06 | B11: Economic & Human Geography | C11: Agriculture, Minerals, Industries, Transportation, Population | D11: Medium | E11: Not Started | F11: =IF(G11>0, G11/8, 0) | G11: 0 | H11: No | I11: No | J11: No

Sheet Indian Polity
A1: INDIAN POLITY - CHAPTER SYLLABUS & TRACKER
A2: Select Status and Revision drop-downs. Enter Practice Marks to auto-calculate percentages.
A4: Total Chapters: | B4: =COUNTA(A6:A11) | D4: Completed: | E4: =COUNTIF(E6:E11, "Completed") | G4: Progress %: | H4: =E4/B4 | J4: Avg Practice Score: | K4: =AVERAGE(F6:F11)
A5: Chapter Code | B5: Chapter Title | C5: Sub-topics & Key Concepts | D5: Priority | E5: Status (Checkmark) | F5: Practice Score (%) | G5: Practice Marks (Obtained / Max) | H5: Revision 1 | I5: Revision 2 | J5: Revision 3 | K5: Notes / Weak Areas
A6: Ch 01 | B6: Constitutional Framework | C6: Making of Constitution, Preamble, Schedules, Features, Sources | D6: Medium | E6: Not Started | F6: =IF(G6>0, G6/10, 0) | G6: 0 | H6: No | I6: No | J6: No
A7: Ch 02 | B7: Rights, Duties & Principles | C7: Fundamental Rights, DPSP, Fundamental Duties, Citizenship | D7: High | E7: Not Started | F7: =IF(G7>0, G7/12, 0) | G7: 0 | H7: No | I7: No | J7: No
A8: Ch 03 | B8: Union Executive & Legislature | C8: President, Vice-President, Prime Minister, Parliament, Parliamentary Committees | D8: High | E8: Not Started | F8: =IF(G8>0, G8/15, 0) | G8: 0 | H8: No | I8: No | J8: No
A9: Ch 04 | B9: State Executive & Legislature | C9: Governor, Chief Minister, State Assembly & Council | D9: Medium | E9: Not Started | F9: =IF(G9>0, G9/8, 0) | G9: 0 | H9: No | I9: No | J9: No
A10: Ch 05 | B10: Judiciary | C10: Supreme Court, High Courts, Subordinate Courts, Judicial Review & Activism | D10: Medium | E10: Not Started | F10: =IF(G10>0, G10/10, 0) | G10: 0 | H10: No | I10: No | J10: No
A11: Ch 06 | B11: Local Government & Bodies | C11: Panchayati Raj, Municipalities, Election Commission, UPSC, CAG, NITI Aayog | D11: Medium | E11: Not Started | F11: =IF(G11>0, G11/10, 0) | G11: 0 | H11: No | I11: No | J11: No

Sheet Indian Economy
A1: INDIAN ECONOMY - CHAPTER SYLLABUS & TRACKER
A2: Select Status and Revision drop-downs. Enter Practice Marks to auto-calculate percentages.
A4: Total Chapters: | B4: =COUNTA(A6:A10) | D4: Completed: | E4: =COUNTIF(E6:E10, "Completed") | G4: Progress %: | H4: =E4/B4 | J4: Avg Practice Score: | K4: =AVERAGE(F6:F10)
A5: Chapter Code | B5: Chapter Title | C5: Sub-topics & Key Concepts | D5: Priority | E5: Status (Checkmark) | F5: Practice Score (%) | G5: Practice Marks (Obtained / Max) | H5: Revision 1 | I5: Revision 2 | J5: Revision 3 | K5: Notes / Weak Areas
A6: Ch 01 | B6: Economic Basics & National Income | C6: GDP, GNP, NNP, Inflation, Deflation, Business Cycles | D6: Medium | E6: Not Started | F6: =IF(G6>0, G6/10, 0) | G6: 0 | H6: No | I6: No | J6: No
A7: Ch 02 | B7: Banking & Monetary Policy | C7: RBI, Repo Rate, Cash Reserve Ratio, Commercial Banks, NPA, Financial Inclusion | D7: High | E7: Not Started | F7: =IF(G7>0, G7/12, 0) | G7: 0 | H7: No | I7: No | J7: No
A8: Ch 03 | B8: Fiscal Policy & Public Finance | C8: Union Budget, Revenue & Capital Deficits, GST, Finance Commission | D8: Medium | E8: Not Started | F8: =IF(G8>0, G8/10, 0) | G8: 0 | H8: No | I8: No | J8: No
A9: Ch 04 | B9: Planning & Economic Development | C9: Five Year Plans, NITI Aayog, Poverty, Unemployment, HDI | D9: Medium | E9: Not Started | F9: =IF(G9>0, G9/8, 0) | G9: 0 | H9: No | I9: No | J9: No
A10: Ch 05 | B10: External Sector & International Trade | C10: BOP, Forex Reserves, FDI, FII, WTO, IMF, World Bank | D10: Medium | E10: Not Started | F10: =IF(G10>0, G10/8, 0) | G10: 0 | H10: No | I10: No | J10: No

Sheet General Knowledge
A1: GENERAL KNOWLEDGE - CHAPTER SYLLABUS & TRACKER
A2: Select Status and Revision drop-downs. Enter Practice Marks to auto-calculate percentages.
A4: Total Chapters: | B4: =COUNTA(A6:A9) | D4: Completed: | E4: =COUNTIF(E6:E9, "Completed") | G4: Progress %: | H4: =E4/B4 | J4: Avg Practice Score: | K4: =AVERAGE(F6:F9)
A5: Chapter Code | B5: Chapter Title | C5: Sub-topics & Key Concepts | D5: Priority | E5: Status (Checkmark) | F5: Practice Score (%) | G5: Practice Marks (Obtained / Max) | H5: Revision 1 | I5: Revision 2 | J5: Revision 3 | K5: Notes / Weak Areas
A6: Ch 01 | B6: Defense & Security Forces | C6: Indian Armed Forces Commands, Weapons, Exercises, Defense Academies | D6: High | E6: Not Started | F6: =IF(G6>0, G6/12, 0) | G6: 0 | H6: No | I6: No | J6: No
A7: Ch 02 | B7: Space & Technology | C7: ISRO Missions, DRDO Technologies, Satellites, Missiles | D7: Medium | E7: Not Started | F7: =IF(G7>0, G7/10, 0) | G7: 0 | H7: No | I7: No | J7: No
A8: Ch 03 | B8: Awards, Honours & Sports | C8: Gallantry Awards, Bharat Ratna, Nobel Prize, National Games, Olympics | D8: Medium | E8: Not Started | F8: =IF(G8>0, G8/8, 0) | G8: 0 | H8: No | I8: No | J8: No
A9: Ch 04 | B9: Books, Authors & Static GK | C9: Famous Books, National Parks, Wildlife Sanctuaries, Important Days | D9: Medium | E9: Not Started | F9: =IF(G9>0, G9/8, 0) | G9: 0 | H9: No | I9: No | J9: No
